spinny.py
spinny-1.1.0.dist-info/LICENSE
spinny-1.1.0.dist-info/WHEEL
spinny-1.1.0.dist-info/METADATA
spinny-1.1.0.dist-info/RECORD
