Metadata-Version: 2.1
Name: spinny
Version: 1.1.0
Summary: A simple spinner library.
Home-page: https://github.com/techieji/spin
Author: Pradhyum R
Author-email: drpradhyum2016@outlook.com
Classifier: License :: OSI Approved :: MIT License
